django_cf/__init__.py
django_cf/db/__init__.py
django_cf/db/base_engine.py
django_cf/db/backends/__init__.py
django_cf/db/backends/d1/__init__.py
django_cf/db/backends/d1/base.py
django_cf/db/backends/do/__init__.py
django_cf/db/backends/do/base.py
django_cf/db/backends/do/storage.py
django_cf/middleware/CloudflareAccessMiddleware.py
django_cf/middleware/__init__.py
django_cf/storage/__init__.py
django_cf/storage/r2.py
django_cf-0.2.9.dist-info/licenses/LICENSE
django_cf-0.2.9.dist-info/METADATA
django_cf-0.2.9.dist-info/WHEEL
django_cf-0.2.9.dist-info/top_level.txt
django_cf-0.2.9.dist-info/RECORD
