Metadata-Version: 2.4
Name: django-cf
Version: 0.2.9
Summary: django-cf is a package that integrates Django with Cloudflare products
Author: Gabriel Massadas
License-Expression: MIT
Project-URL: Homepage, https://github.com/G4brym/django-cf
Project-URL: Bug Reports, https://github.com/G4brym/django-cf/issues
Project-URL: Source, https://github.com/G4brym/django-cf
Classifier: Development Status :: 3 - Alpha
Classifier: Framework :: Django
Classifier: Framework :: Django :: 5.0
Classifier: Operating System :: OS Independent
Classifier: Programming Language :: Python
Classifier: Programming Language :: Python :: 3
Classifier: Programming Language :: Python :: 3.12
Requires-Python: >=3.12
License-File: LICENSE
Requires-Dist: sqlparse
Provides-Extra: dev
Requires-Dist: pytest; extra == "dev"
Requires-Dist: requests; extra == "dev"
Requires-Dist: ruff; extra == "dev"
Requires-Dist: django; extra == "dev"
Dynamic: license-file
